{"cameraMode":{"drawMode":0,"name":"Shaded","section":"Shading Mode"},"sceneLighting":true,"audioPlay":false,"sceneViewState":{"m_AlwaysRefresh":false,"showFog":true,"showSkybox":true,"showFlares":true,"showImageEffects":true,"showParticleSystems":true,"showVisualEffectGraphs":true,"m_FxEnabled":true},"in2DMode":false,"pivot":{"x":-0.09999728202819824,"y":2.2547712326049806,"z":-9.93548583984375},"rotation":{"x":0.49157893657684328,"y":0.001308776205405593,"z":-0.0007340865558944643,"w":0.8708415031433106},"size":6.7205963134765629,"orthographic":false}